msvc_framework/__init__.py
msvc_framework/decorator.py
msvc_framework/fields.py
msvc_framework/serializers.py
msvc_framework/tasks.py
msvc_framework/utils.py
msvc_framework/broker/__init__.py
msvc_framework/broker/exceptions.py
msvc_framework/broker/interface.py
msvc_framework/broker/kafka.py
msvc_framework/management/__init__.py
msvc_framework/management/commands/__init__.py
msvc_framework/management/commands/subscribe.py
msvc_framework-0.0.1.dist-info/LICENSE
msvc_framework-0.0.1.dist-info/METADATA
msvc_framework-0.0.1.dist-info/WHEEL
msvc_framework-0.0.1.dist-info/top_level.txt
msvc_framework-0.0.1.dist-info/RECORD
