Metadata-Version: 2.1
Name: msvc-framework
Version: 0.0.1
Summary: Microservice for django
Home-page: https://github.com/myrubapa/msvc_framework
Author: Bekhzod Tillakhanov
Author-email: bekhzod.tillakhanov@gmail.com
License: UNKNOWN
Platform: UNKNOWN
Classifier: Programming Language :: Python :: 3
Classifier: License :: OSI Approved :: MIT License
Classifier: Operating System :: OS Independent
Requires-Python: >=3.5
Requires-Dist: Django
Requires-Dist: djangorestframework
